MANIFEST.in
README
README.rst
di.py
setup.py
python_simple_di.egg-info/PKG-INFO
python_simple_di.egg-info/SOURCES.txt
python_simple_di.egg-info/dependency_links.txt
python_simple_di.egg-info/pbr.json
python_simple_di.egg-info/top_level.txt