Metadata-Version: 1.1
Name: python-simple-di
Version: 1.5.3
Summary: A simple dependency injection container.
Home-page: http://bitbucket.org/jblawatt/python-simple-di/
Author: Jens Blawatt
Author-email: jblawatt@googlemail.com
License: MIT
Platform: UNKNOWN
Classifier: Development Status :: 5 - Production/Stable
Classifier: License :: OSI Approved :: MIT License
Classifier: Topic :: Utilities
Classifier: Programming Language :: Python :: 2
Classifier: Programming Language :: Python :: 2.7
Classifier: Programming Language :: Python :: 3
Classifier: Programming Language :: Python :: 3.2
Classifier: Programming Language :: Python :: 3.3
Classifier: Operating System :: OS Independent
